dnplab/__init__.py
dnplab/version.py
dnplab/analysis/__init__.py
dnplab/analysis/hydration.py
dnplab/analysis/peaks.py
dnplab/analysis/relaxation_fit.py
dnplab/analysis/simulate_enhancement_profiles.py
dnplab/config/__init__.py
dnplab/config/config.py
dnplab/config/dnplab.cfg
dnplab/constants/__init__.py
dnplab/constants/constants.py
dnplab/constants/mrProperties.py
dnplab/constants/radicalProperties.py
dnplab/core/__init__.py
dnplab/core/base.py
dnplab/core/coord.py
dnplab/core/data.py
dnplab/core/ufunc.py
dnplab/core/util.py
dnplab/fitting/__init__.py
dnplab/fitting/general.py
dnplab/io/__init__.py
dnplab/io/bes3t.py
dnplab/io/cnsi.py
dnplab/io/delta.py
dnplab/io/h5.py
dnplab/io/load.py
dnplab/io/load_csv.py
dnplab/io/logs.py
dnplab/io/mat.py
dnplab/io/power.py
dnplab/io/prospa.py
dnplab/io/random.py
dnplab/io/rs2d.py
dnplab/io/save.py
dnplab/io/specman.py
dnplab/io/tnmr.py
dnplab/io/topspin.py
dnplab/io/vna.py
dnplab/io/vnmrj.py
dnplab/io/winepr.py
dnplab/math/__init__.py
dnplab/math/lineshape.py
dnplab/math/pulses.py
dnplab/math/relaxation.py
dnplab/math/window.py
dnplab/plotting/__init__.py
dnplab/plotting/colors.py
dnplab/plotting/general.py
dnplab/plotting/image.py
dnplab/plotting/stack_plot.py
dnplab/processing/__init__.py
dnplab/processing/align.py
dnplab/processing/apodization.py
dnplab/processing/average.py
dnplab/processing/conversion.py
dnplab/processing/fft.py
dnplab/processing/helpers.py
dnplab/processing/integration.py
dnplab/processing/interpolation.py
dnplab/processing/offset.py
dnplab/processing/phase.py
dnplab/reporting/__init__.py
dnplab/widgets/__init__.py
dnplab/widgets/align_widget.py
dnplab/widgets/phase_widget.py
dnplab-2.3.6.dist-info/licenses/LICENSE.txt
unittests/__init__.py
unittests/test_average.py
unittests/test_data_class.py
unittests/test_dnp_nmr.py
unittests/test_dnp_tools.py
unittests/test_fft.py
unittests/test_general_fit.py
unittests/test_hydration.py
unittests/test_io.py
unittests/test_load.py
unittests/test_m_math.py
unittests/test_nddata_core.py
dnplab-2.3.6.dist-info/METADATA
dnplab-2.3.6.dist-info/WHEEL
dnplab-2.3.6.dist-info/top_level.txt
dnplab-2.3.6.dist-info/RECORD
