Metadata-Version: 2.4
Name: dnplab
Version: 2.3.6
Summary: DNPLab - Bringing the Power of Python to DNP-NMR Spectroscopy
Home-page: http://dnpLab.net
Download-URL: 
Author: DNPLab Team
License: MIT
Project-URL: Documentation, http://docs.dnpLab.net
Project-URL: Examples, http://dnplab.net/auto_examples/index.html
Project-URL: Source Code, https://github.com/DNPLab/dnplab
Project-URL: Web App, http://odnplab.com/
Keywords: ODNP,DNP,NMR
Classifier: Development Status :: 3 - Alpha
Classifier: License :: OSI Approved :: MIT License
Classifier: Programming Language :: Python :: 3.10
Classifier: Programming Language :: Python :: 3.11
Requires-Python: >=3.10
License-File: LICENSE.txt
Requires-Dist: numpy>=2.0.0
Requires-Dist: scipy>=1.14.0
Requires-Dist: matplotlib>=3.9.1
Requires-Dist: h5py>=3.11.0
Dynamic: author
Dynamic: classifier
Dynamic: description
Dynamic: description-content-type
Dynamic: home-page
Dynamic: keywords
Dynamic: license
Dynamic: license-file
Dynamic: project-url
Dynamic: requires-dist
Dynamic: requires-python
Dynamic: summary
